{"cameraMode":{"drawMode":0,"name":"Shaded","section":"Shading Mode"},"sceneLighting":false,"audioPlay":false,"sceneViewState":{"m_AlwaysRefresh":false,"showFog":true,"showSkybox":false,"showFlares":true,"showImageEffects":true,"showParticleSystems":true,"showVisualEffectGraphs":true,"m_FxEnabled":false},"in2DMode":false,"pivot":{"x":3.8737077713012697,"y":-1.2042665481567383,"z":-1.0899162292480469},"rotation":{"x":-0.08497022092342377,"y":-0.9125046730041504,"z":0.24519091844558717,"w":-0.3162325918674469},"size":4.798266887664795,"orthographic":false}